recordio/__init__.py
recordio/recordio.py
recordio/recordio_test.py
recordio/varint.py
recordio/varint_test.py
recordio_py-0.2.0.dist-info/LICENSE
recordio_py-0.2.0.dist-info/METADATA
recordio_py-0.2.0.dist-info/WHEEL
recordio_py-0.2.0.dist-info/top_level.txt
recordio_py-0.2.0.dist-info/RECORD
