Metadata-Version: 2.1
Name: recordio-py
Version: 0.2.0
Summary: Recordio reader/writer
Author-email: Chris Lamb <chlamb16@gmail.com>
License: MIT License        
Project-URL: Homepage, https://github.com/chris-lamb/recordio
Keywords: recordio
Classifier: License :: OSI Approved :: MIT License
Classifier: Programming Language :: Python
Classifier: Programming Language :: Python :: 3
Classifier: Programming Language :: Python :: 3.8
Classifier: Programming Language :: Python :: 3.9
Classifier: Programming Language :: Python :: 3.10
Requires-Python: >=3.8
License-File: LICENSE
Provides-Extra: dev
Requires-Dist: coverage ; extra == 'dev'
Requires-Dist: tox ; extra == 'dev'
